workflows_manager/__init__.py
workflows_manager/__version__.py
workflows_manager/command_arguments.py
workflows_manager/configuration.py
workflows_manager/dispatcher.py
workflows_manager/exceptions.py
workflows_manager/logger.py
workflows_manager/main.py
workflows_manager/workflow.py
workflows_manager/actions/__init__.py
workflows_manager/actions/list.py
workflows_manager/actions/misc.py
workflows_manager/actions/runner.py
workflows_manager/actions/validator.py
workflows_manager/utils/__init__.py
workflows_manager/utils/reference_resolver.py
workflows_manager-0.4.1.dist-info/METADATA
workflows_manager-0.4.1.dist-info/WHEEL
workflows_manager-0.4.1.dist-info/entry_points.txt
workflows_manager-0.4.1.dist-info/licenses/LICENSE.md
workflows_manager-0.4.1.dist-info/RECORD
