Metadata-Version: 2.4
Name: workflows-manager
Version: 0.4.1
Summary: Python CLI application that allows to run custom workflows.
Project-URL: Documentation, https://dl1998.github.io/workflows-manager
Project-URL: Repository, https://github.com/dl1998/workflows-manager.git
Project-URL: Issues, https://github.com/dl1998/workflows-manager/issues
Author-email: Dmytro Leshchenko <dima.leschenko1998@gmail.com>
Maintainer-email: Dmytro Leshchenko <dima.leschenko1998@gmail.com>
License-Expression: MIT
License-File: LICENSE.md
Keywords: action,manager,pipeline,pipelines,step,workflow,workflows,workflows-manager
Classifier: Development Status :: 4 - Beta
Classifier: Environment :: Console
Classifier: Intended Audience :: Developers
Classifier: Intended Audience :: Information Technology
Classifier: Intended Audience :: Other Audience
Classifier: Intended Audience :: System Administrators
Classifier: License :: OSI Approved :: MIT License
Classifier: Operating System :: OS Independent
Classifier: Programming Language :: Python :: 3
Classifier: Programming Language :: Python :: 3.9
Classifier: Programming Language :: Python :: 3.10
Classifier: Programming Language :: Python :: 3.11
Classifier: Programming Language :: Python :: 3.12
Classifier: Programming Language :: Python :: 3.13
Classifier: Topic :: Software Development :: Build Tools
Classifier: Topic :: Software Development :: Libraries :: Application Frameworks
Classifier: Topic :: System
Classifier: Topic :: Utilities
Classifier: Typing :: Typed
Requires-Python: >=3.9
Requires-Dist: pyyaml==6.0.2
